pyBADA/TCL.py
pyBADA/__init__.py
pyBADA/aircraft.py
pyBADA/atmosphere.py
pyBADA/bada3.py
pyBADA/bada4.py
pyBADA/badaH.py
pyBADA/configuration.py
pyBADA/constants.py
pyBADA/conversions.py
pyBADA/flightTrajectory.py
pyBADA/geodesic.py
pyBADA/magnetic.py
pyBADA/trajectoryPrediction.py
pyBADA/utils.py
pyBADA/data/magneticDeclinationGridData.json
pyBADA/aircraft/BADA3/DUMMY/BADA.GPF
pyBADA/aircraft/BADA3/DUMMY/BZJT__.APF
pyBADA/aircraft/BADA3/DUMMY/BZJT__.OPF
pyBADA/aircraft/BADA3/DUMMY/BZJT__.PTD
pyBADA/aircraft/BADA3/DUMMY/BZJT__.PTF
pyBADA/aircraft/BADA3/DUMMY/GA____.APF
pyBADA/aircraft/BADA3/DUMMY/GA____.OPF
pyBADA/aircraft/BADA3/DUMMY/GA____.PTD
pyBADA/aircraft/BADA3/DUMMY/GA____.PTF
pyBADA/aircraft/BADA3/DUMMY/J2H___.APF
pyBADA/aircraft/BADA3/DUMMY/J2H___.OPF
pyBADA/aircraft/BADA3/DUMMY/J2H___.PTD
pyBADA/aircraft/BADA3/DUMMY/J2H___.PTF
pyBADA/aircraft/BADA3/DUMMY/J2M___.APF
pyBADA/aircraft/BADA3/DUMMY/J2M___.OPF
pyBADA/aircraft/BADA3/DUMMY/J2M___.PTD
pyBADA/aircraft/BADA3/DUMMY/J2M___.PTF
pyBADA/aircraft/BADA3/DUMMY/J4H___.APF
pyBADA/aircraft/BADA3/DUMMY/J4H___.OPF
pyBADA/aircraft/BADA3/DUMMY/J4H___.PTD
pyBADA/aircraft/BADA3/DUMMY/J4H___.PTF
pyBADA/aircraft/BADA3/DUMMY/ReleaseSummary
pyBADA/aircraft/BADA3/DUMMY/SYNONYM.NEW
pyBADA/aircraft/BADA3/DUMMY/TP2M__.APF
pyBADA/aircraft/BADA3/DUMMY/TP2M__.OPF
pyBADA/aircraft/BADA3/DUMMY/TP2M__.PTD
pyBADA/aircraft/BADA3/DUMMY/TP2M__.PTF
pyBADA/aircraft/BADA4/DUMMY/ACM_BADA4.xsd
pyBADA/aircraft/BADA4/DUMMY/GPF.xml
pyBADA/aircraft/BADA4/DUMMY/GPF_BADA4.xsd
pyBADA/aircraft/BADA4/DUMMY/Dummy-PST/Dummy-PST.ATF
pyBADA/aircraft/BADA4/DUMMY/Dummy-PST/Dummy-PST.xml
pyBADA/aircraft/BADA4/DUMMY/Dummy-PST/Dummy-PST_ISA+20.PTD
pyBADA/aircraft/BADA4/DUMMY/Dummy-PST/Dummy-PST_ISA+20.PTF
pyBADA/aircraft/BADA4/DUMMY/Dummy-PST/Dummy-PST_ISA.PTD
pyBADA/aircraft/BADA4/DUMMY/Dummy-PST/Dummy-PST_ISA.PTF
pyBADA/aircraft/BADA4/DUMMY/Dummy-TBP/Dummy-TBP.ATF
pyBADA/aircraft/BADA4/DUMMY/Dummy-TBP/Dummy-TBP.xml
pybada-0.1.7.dist-info/METADATA
pybada-0.1.7.dist-info/WHEEL
pybada-0.1.7.dist-info/licenses/AUTHORS
pybada-0.1.7.dist-info/licenses/LICENCE.txt
pybada-0.1.7.dist-info/RECORD
