Metadata-Version: 2.4
Name: pyBADA
Version: 0.1.7
Summary: Aircraft performance modelling, trajectory prediction and optimisation, and visualisation with EUROCONTROL's BADA.
Project-URL: Homepage, https://github.com/eurocontrol-bada/pybada
Author-email: Henrich Glaser-Opitz <henrich.glaser-opitz@eurocontrol.int>, Antonio Vivace <antonio.vivace@eurocontrol.int>
License: EUPL-1.2
License-File: AUTHORS
License-File: LICENCE.txt
Classifier: License :: OSI Approved :: European Union Public Licence 1.2 (EUPL 1.2)
Classifier: Programming Language :: Python :: 3
Requires-Python: >=3.12
Requires-Dist: numpy>=2.3.2
Requires-Dist: pandas>=2.3.2
Requires-Dist: scipy>=1.16.1
Requires-Dist: simplekml>=1.3.6
Requires-Dist: xarray>=2025.9.0
Requires-Dist: xlsxwriter>=3.2.5
Provides-Extra: dev
Requires-Dist: build; extra == 'dev'
Requires-Dist: folium==0.20.0; extra == 'dev'
Requires-Dist: matplotlib==3.10.6; extra == 'dev'
Requires-Dist: pre-commit==4.2.0; extra == 'dev'
Requires-Dist: pytest==8.4.2; extra == 'dev'
Requires-Dist: readthedocs-sphinx-search>=0.3.2; extra == 'dev'
Requires-Dist: ruff==0.12.12; extra == 'dev'
Requires-Dist: sphinx-gallery==0.19.0; extra == 'dev'
Requires-Dist: sphinx-rtd-theme==3.0.2; extra == 'dev'
Requires-Dist: sphinx==8.2.3; extra == 'dev'
Requires-Dist: twine; extra == 'dev'
